Workbook

Sheet Показатели 2026
A1: Выполнение плана подбора | B1: нач.2026 | C1: 1кв | E1: 2кв | G1: 3кв | I1: 4кв | K1: итог 2026 | O1: Эффективность каналов поиска персонала (все кандидаты) 2026 | P1: шт. | Q1: %
B2: план | C2: план | D2: факт | E2: план | F2: факт | G2: план | H2: факт | I2: план | J2: факт | K2: план | L2: факт
A3: Вакансии, шт | B3: ='Рекрутинг '!E261 | C3: ='Рекрутинг '!F261 | D3: 94 | E3: ='Рекрутинг '!H261 | F3: 71 | G3: 76 | H3: 55 | I3: 74 | J3: =#REF! | K3: =C3+E3+G3+I3 | L3: =D3+F3+H3+J3 | O3: Отклик на HH.ru | P3: ='Рекрутинг '!B264 | Q3: ='Рекрутинг '!C264
A4: % выполнения плана | C4: =D3/C3 | E4: =F3/E3 | G4: =H3/G3 | I4: =J3/I3 | K4: =L3/K3 | O4: Прямой поиск на HH.ru | P4: ='Рекрутинг '!B265 | Q4: ='Рекрутинг '!C265
O5: Рекомендации (внешн., реферальная программа) | P5: ='Рекрутинг '!B266 | Q5: ='Рекрутинг '!C266
B6: 1кв. | C6: 2кв. | D6: 3кв. | E6: 4кв. | F6: всего | O6: ВУЗы | P6: ='Рекрутинг '!B267 | Q6: ='Рекрутинг '!C267
A7: Текучесть персонала поквартально | B7: ='Текучесть расчетный файл 2026'!B11 | C7: ='Текучесть расчетный файл 2026'!D11 | D7: ='Текучесть расчетный файл 2026'!B21 | E7: ='Текучесть расчетный файл 2026'!D21 | F7: =SUM(B7:C7) | O7: Сайт компании (раздел о вакансиях) | P7: ='Рекрутинг '!B268 | Q7: ='Рекрутинг '!C268
O8: Перевод внутри ГК | P8: ='Рекрутинг '!B269 | Q8: ='Рекрутинг '!C269
A9: Коэффициент принятия офферов 3-й кв. | B9: оффер,шт | C9: выходы,шт. | D9: отказ, шт. | E9: коэф. | O9: Отклик на другой площадке (ВК и т.д.) | P9: ='Рекрутинг '!B270 | Q9: ='Рекрутинг '!C270
B10: 66 | C10: 55 | D10: 11 | E10: =C10/B10 | O10: Отклик на JobLab | P10: ='Рекрутинг '!B271 | Q10: ='Рекрутинг '!C271
O11: Другой | P11: ='Рекрутинг '!B272 | Q11: ='Рекрутинг '!C272
A12: Конверсия писем по кандидатам за 3-й кв. | B12: Вакансии | C12: Отправлено писем | D12: % открытия | E12: Получено ответов | O12: Всего | P12: =SUM(P3:P11) | Q12: ='Рекрутинг '!C273
A13: Всего по отчету | B13: 82 | C13: 913 | D13: 0.77 | E13: 260
O14: Статистика причин отказов
A15: Назначенные интервью за 3-й кв. | B15: Назначено | C15: Отменено | O15: Причины отказов | P15: шт.
B16: 387 | C16: 0.09 | O16: Overqualified | P16: 9
O17: Вакансия закрыта/приостановлена | P17: 557
A18: Проектная работа | C18: Статус | O18: Долго на этапе | P18: 578
A19: Кадровой делопроизводство | O19: Не прошел СБ | P19: 9
A20: Переход на КЭДО | C20: в процессе | O20: Отказ (нет вакансии) | P20: 21
A21: Восстановление КДП 2025 + 2024 частично | C21: в процессе | O21: Отклонен заказчиком (личностные качества) | P21: 58
A22: Организационная структура и штатное расписание | C22: в процессе | O22: Отклонен заказчиком (уровень квалификации) | P22: 374
A23: Актуализация ДИ | C23: в процессе | O23: Отклонен заказчиком (фин. ожидания) | P23: 28
A24: Актуализация ЛНА | C24: в процессе | O24: Отклонен заказчиком по резюме | P24: 395
A25: Рекрутинг | O25: Отклонен после тестирования | P25: 1
A26: Выстраивание системы адаптации и наставничества (Положения) | C26: в процессе | O26: Отклонен рекрутером (график) | P26: 4
A27: Разработка и проведение внутреннего обучения по подбору персонала для руководителей | C27: в процессе | O27: Отклонен рекрутером (личностные качества) | P27: 54
A28: Проект "Кадровый резерв АИ СН" | C28: в процессе | O28: Отклонен рекрутером (по истории) | P28: 15
A29: Летний корпоратив АИ СН + ЦТП | C29: выполнено | O29: Отклонен рекрутером (уровень квалификации) | P29: 141
A30: Актуализация реферальной программы | C30: выполнено | O30: Отклонен рекрутером (фин. ожидания) | P30: 21
A31: Ввыстраивание системы коммуникаций с сотрудником на ИС (разработка и внедрение чек-листа) | C31: в процессе | O31: Отклонен рекрутером по резюме | P31: 112
A32: Развитие взаимодействия с ВУЗами и ССУЗами | C32: в процессе | O32: Перевод на другую вакансию | P32: 164
O33: Плохие рекомендации | P33: 13
O34: Самоотказ (выбрал др. оффер) | P34: 49
O35: Самоотказ (график) | P35: 43
O36: Самоотказ (контроффер от текущего работодателя) | P36: 7
O37: Самоотказ (не в поиске/приостановил) | P37: 323
O38: Самоотказ (не вышел на связь) | P38: 1353
O39: Самоотказ (не оч. интересный функционал) | P39: 65
O40: Самоотказ (не пришел на собеседование) | P40: 66
O41: Самоотказ (неудобно добираться) | P41: 243
O42: Самоотказ (отзывы о компании) | P42: 1
O43: Самоотказ (уровень дохода) | P43: 177
O44: Самоотказ (уровень квалификации) | P44: 13
... O46: По другой причине | P46: 192

Sheet Рекрутинг 
A1: Отдел | B1: Участок/группа | C1: Город | D1: Должность | E1: нач. 2026 | F1: 1 кв 2026 | H1: 2 кв 2026 | J1: 3 кв 2026 | L1: 4 кв 2026
E2: Кол-во по плану, шт. | F2: Кол-во по плану, шт. | G2: Кол-во трудоустроенных | H2: Кол-во по плану, шт. | I2: Кол-во трудоустроенных | J2: Кол-во по плану, шт. | K2: Кол-во трудоустроенных | L2: Кол-во по плану, шт. | M2: Кол-во трудоустроенных
A3: Отдел дизайна | C3: Москва | D3: Промышленный дизайнер | E3: 1 | F3: 0 | H3: 0
D4: Специалист по документообороту | I4: 1
A5: КБ и ОГК | C5: Москва | D5: Начальник КБ | E5: 1 | F5: 1 | G5: 1 | H5: 0
A6: КБ и ОГК Отдел интерьера | B6: Бригада БКО Бригада обводов Бригада мебели | C6: Москва | D6: ИК1, ИК2 ИК1, ИК2 ВИК, ИК1, ИК2 | E6: 4 | F6: 1 | G6: 1 | H6: 0
C7: Москва | D7: ИК1, ИК2 ИК1, ИК2 ВИК, ИК1, ИК2 | E7: 5 | F7: 1 | G7: 1 | H7: 0
C8: Москва | D8: ИК1, ИК2 ИК1, ИК2 ВИК, ИК1, ИК2 | E8: 5 | F8: 0 | G8: 0 | H8: 0
C9: Москва | D9: ИК1, ИК2 ИК1, ИК2 ВИК, ИК1, ИК2 | E9: 5 | F9: 0 | G9: 4 | H9: 0
C10: Ульяновск | D10: ИК1, ИК2 ИК1, ИК2 ВИК, ИК1, ИК3 | I10: 3
C11: Казань | D11: ИК1, ИК2 ИК1, ИК2 ВИК, ИК1, ИК2 | L11: 1
C12: Жуковский | D12: ИК1, ИК2 ИК1, ИК2 ВИК, ИК1, ИК2 | L12: 1
A13: КБ и ОГК БЭО | B13: Бригада электросхем | C13: Москва | D13: Ведущий инженер-электрик Инженер-электрик 1 категории | E13: 2 | F13: 0 | G13: 0 | H13: 0 | K13: 1
A14: КБ и ОГК ЭТД | B14: отдел ЭТД | C14: Москва | D14: Инженер-конструктор 2 категории отдела ЭТД (РЭ, КДСЕ) | E14: 2 | F14: 3 | G14: 1 | H14: 0
A15: КБ и ОГК Отдел технической документации | C15: Москва | D15: Начальник отдела | E15: 1 | F15: 1 | G15: 1 | H15: 0
A16: КБ и ОГК Отдел общего проектирования (ООП) | C16: Москва | D16: Инеженр-конструктор | E16: 1 | F16: 1 | G16: 1 | H16: 0 | L16: 1
A17: КБ и ОГК Отдел прочности | C17: Москва | D17: Инженер по прочности | E17: 1 | F17: 1 | G17: 0 | H17: 0
A18: КБ и ОГК Отдел нормоконтроля | C18: Москва | D18: Ведущий инженер по стандартизации | E18: 1 | F18: 1 | G18: 0 | H18: 0
C19: Москва | D19: Инженер по стандартизации 1 категории | E19: 1 | F19: 0 | G19: 0 | H19: 0
A20: КБ и ОГК Отдел главного конструктора (ОГК) | C20: Москва | D20: Менеджер проекта | E20: 1 | F20: 0 | G20: 0 | H20: 0
C21: Москва | D21: Ведущий ИК или ведущий специалист в ОГК | E21: 1 | F21: 1 | G21: 1 | H21: 2 | I21: 1
A22: КБ и ОГК Отдел разработки кресел авиационных | D22: Ведущий инженер-конструктор | G22: 1 | H22: 0 | L22: 1
A23: Отдел главного технолога | B23: Бюро подготовки производства | C23: Москва | D23: Ведущий инженер-технолог (расцеховки) | E23: 1 | F23: 1 | G23: 1 | H23: 1 | J23: 2 | L23: 2
B24: Бюро подготовки производства | C24: Москва | D24: Инженер-технолог (расцеховки) | E24: 1 | F24: 1 | G24: 1
B25: Технологический отдел | C25: Москва | D25: Ведущий инженер-конструктор по технологической оснастке | E25: 1 | F25: 1 | G25: 1 | I25: 2
B26: Технологический отдел | C26: Москва | D26: Инженер-конструктор по технологической оснастке | E26: 1 | F26: 1 | H26: 2 | J26: 1 | L26: 2
B27: Технологический отдел/ Бюро разработки управляющих программ | C27: Москва | D27: Ведущий инженер-технолог ЧПУ | E27: 1 | F27: 1 | G27: 1 | H27: 3 | J27: 1 | K27: 1
B28: Технологический отдел/ Бюро разработки управляющих программ | C28: Москва | D28: Инженер-технолог (инструмент) | K28: 1
B29: Технологический отдел | C29: Москва | D29: Ведущий Инженер-технолог (сборка, композитные материалы) | E29: 1 | F29: 1 | G29: 1 | H29: 2 | J29: 1 | L29: 1
B30: Технологический отдел | C30: Москва | D30: Инженер-технолог (металлобработка) | E30: 1 | F30: 1 | G30: 1 | J30: 3 | L30: 3
B31: Технологический отдел | C31: Москва | D31: Инженер-технолог (металлобработка) | E31: 1 | F31: 1 | G31: 1
B32: Технологический отдел | C32: Москва | D32: Начальник технологического бюро | E32: 1 | F32: 1
B33: Технологический отдел | C33: Москва | D33: Ведущий Инженер-технолог (металлообработка) | E33: 1 | F33: 1
B34: Технологический отдел | C34: Москва | D34: Инженер-технолог по сборке | E34: 1 | F34: 0 | I34: 2
B35: Технологический отдел | C35: Москва | D35: Инженер-технолог по сборке | E35: 1 | F35: 0
B36: Технологический отдел | C36: Москва | D36: Инженер-технолог по сборке | E36: 1 | F36: 0
B37: Технологический отдел | C37: Москва | D37: Инженер-технолог по сборке | E37: 1 | F37: 0
B38: Технологический отдел | C38: Москва | D38: Инженер-технолог (металлобработка) | E38: 1 | F38: 0 | H38: 3 | I38: 1
B39: Технологический отдел | C39: Москва | D39: Инженер-технолог (металлобработка) | E39: 1 | F39: 0 | J39: 2 | K39: 1 | L39: 1
B40: Технологический отдел | C40: Москва | D40: Инженер-технолог (металлобработка) | E40: 1 | F40: 0
B41: Технологический отдел | C41: Москва | D41: Инженер-технолог (металлобработка) | E41: 1 | F41: 0
B42: Технологический отдел | C42: Москва | D42: Инженер-технолог (металлобработка) | E42: 1 | F42: 0
B43: Технологический отдел | C43: Москва | D43: Инженер-технолог (металлобработка) | E43: 1 | F43: 0
B44: Технологический отдел | C44: Москва | D44: Инженер-технолог по сборке | E44: 1 | F44: 0 | J44: 1 | L44: 1
B45: Технологический отдел | C45: Москва | D45: Инженер-технолог по сборке | E45: 1 | F45: 0
B46: Технологический отдел | C46: Москва | D46: Инженер-технолог по композитным изделиям | E46: 1 | F46: 0
B47: Технологический отдел | C47: Москва | D47: Инженер-технолог по мех. обработке композитных изделий | E47: 1 | F47: 0
B48: Технологический отдел | C48: Москва | D48: Инженер-технолог по сборке | E48: 1 | F48: 0 | G48: 1
B49: Технологический отдел | C49: Москва | D49: Инженер-технолог по сборке | E49: 1 | F49: 0
B50: Технологический отдел | C50: Москва | D50: Инженер-технолог по декоративной отделке | E50: 1 | F50: 0 | J50: 1 | L50: 1
B51: Технологический отдел | C51: Москва | D51: Инженер-технолог по швейному производству | E51: 1 | F51: 0
B52: Технологический отдел | C52: Москва | D52: Заместитель главного технолога | G52: 1
B53: Технологический отдел | C53: Москва | D53: Начальник отдела (руднево) | H53: 1 | I53: 1
B54: Технологический отдел | C54: Москва | D54: Ведущий инженер-технолог (нормировщик) | I54: 1
B55: Технологический отдел | C55: Москва | D55: Инженер технолог нормировщик | H55: 1 | J55: 2 | K55: 1 | L55: 1
B56: ПП-5 | C56: Москва | D56: слесарь-сборщик 4 разряда | E56: 2 | F56: 2 | G56: 0 | H56: 2
D57: Инженер по тех.документации | J57: 2 | L57: 2
D58: Заместитель гл.технолога | K58: 1
A59: Департамент ППО | B59: Центральный офис | C59: Москва | D59: Инженер-технолог | E59: 1 | F59: 1 | H59: 2
B60: Отдел планирования и координации проектов | C60: Москва | D60: Начальник отдела | G60: 1
C61: Москва | D61: Ведущий специалист | G61: 1 | H61: 1
C62: Москва | D62: Специалист | G62: 1 | K62: 1
B63: Центральный офис | C63: Москва | D63: Менеджер проектов ППО ГОЗ | E63: 1 | F63: 1 | H63: 1 | I63: 1
B64: ОП Машково | C64: Москва | D64: Инженер-конструктор | E64: 1 | F64: 1 | H64: 4 | I64: 2 | J64: 2 | K64: 2
D65: Начальник бюро тех. | J65: 1 | L65: 1
B66: ОП Машково | C66: Москва | D66: Инженер-технолог | E66: 3 | F66: 1 | J66: 3 | K66: 2 | L66: 1
D67: Менеджер проекта ППО гражданской авиации | I67: 1
A68: ОП Машково (для ППО) | B68: ОП Машково | C68: Москва | D68: ОПР | E68: 10 | F68: 0
B69: ОП Машково | D69: Столяр 4-6 р. | H69: 4
B70: ОП Машково | D70: Маляр 6 р. | H70: 2
B71: ОП Машково | D71: Маляр (Шлифовщик-полировщик) - 4-5р. | H71: 8
B72: ОП Машково | D72: Маляр-оклейщик 4-6р | H72: 2
B73: ОП Машково | D73: Зам.начальника производства по направлению ППО | I73: 1
A74: Дирекция программ | C74: Москва | D74: Руководитель проекта | E74: 2 | F74: 0 | G74: 0 | H74: 1
C75: Москва | D75: Менеджер проекта | E75: 1 | F75: 0 | G75: 0 | J75: 1 | L75: 1
B76: Отдел планирования и контроля | C76: Москва | D76: Начальник отдела | E76: 1 | F76: 1 | G76: 0
C77: Москва | D77: Ведущий специалист | E77: 1 | F77: 1 | G77: 0
A78: Департамент по ИТ и ПО | B78: Отдел ИТ | C78: Москва | D78: Системный администратор | E78: 1 | F78: 1 | G78: 0 | H78: 1
D79: Младший системный администратор | I79: 2 | J79: 1 | K79: 1
D80: Архитектор серверной инфраструктуры | K80: 1
D81: Архитектор сетевой инфраструктуры | K81: 1
D82: Ведущий системный администратор/нач.отдела | L82: 1
C83: Москва | D83: Начальник отдела | E83: 1 | F83: 1 | G83: 1
B84: Отдел АСУП | C84: Москва | D84: Специалист по внедрению | E84: 2 | F84: 0 | G84: 1
C85: Москва | D85: Начальник отдела | G85: 1
C86: Москва | D86: Системный аналитик | E86: 2 | F86: 0 | H86: 1
C87: Москва | D87: Инженер-программист 1С | E87: 2 | F87: 0 | H87: 1 | I87: 1 | J87: 1 | K87: 1
C88: Москва | D88: Администратор 1С | E88: 1 | F88: 0
D89: руководитель проекта | I89: 1
D90: Руководитель направления НСИ | I90: 1
D91: Ведущий бизнес-аналитик | I91: 1
D92: Ведущий специалист по сопровождению информационных систем жизненного цикла изделия | I92: 1
D93: Аналитик 1С | K93: 1
D94: Руководитель группы управления ЖЦИ | K94: 1
A95: Отдел подбора и развития персонала | C95: Москва | D95: Ведущий менеджер по подбору и развитию персонала | E95: 1 | F95: 1
C96: Москва | D96: Менеджер по корп.коммуникациям | E96: 1 | F96: 1 | G96: 1 | J96: 1 | L96: 1
D97: Менеджер по подбору персонала | G97: 1 | K97: 1
A98: Отдел управления персоналом | C98: Москва | D98: Младший специалист | G98: 1
C99: Москва | D99: Ведущий специалист по воинскому учету | G99: 1
C100: Москва | D100: Ведущий менеджер по персоналу | I100: 1
...

Sheet Иные направления
A1: Задача | B1: Уточнения по задаче | C1: Цель | D1: Ответственный | E1: Результат
A2: ФАКТ 1 квартал 2026
A3: Директор по персоналу
A4: Организационная структура | B4: Утверждение структуры у руководства, организация ее исполнения | C4: Организация деятельности компании | D4: Пенский А.К. | E4: Утверждена "переходная" организационная структура Общества
A5: Организация дополнительных гарантий работникам. Питание на производстве (на производственных площадках Общества) | B5: Заключение договора, организация поставок, оплаты, решение возникающих вопросов | C5: Соблюдение законодательства РФ, гарантии работникам | D5: Пенский А.К. | E5: Заключен договор на поставку питания на Машково и Руднево
A6: Решение слоных вопросов | B6: Сложные увольнения | C6: Соблюдение законодательства РФ, гарантии работникам | D6: Пенский А.К. | E6: Решены вопросы по 3 сложным увольнениям (Кравцов, Яворский, Тимохин)
A7: Участие в реализации стратегических целей | B7: Обеспечение персоналом роста товарной программы | C7: Планирование подбора | D7: Пенский А.К. | E7: Согласование актуализации плана подбора в производстве
A8: Оптимизация процессов | B8: Рационализация кроссфункциональных процессов | C8: Оптимизация сроков документооборота | D8: Пенский А.К. | E8: БП премирование, отчетность по питанию, согласование табелей
A9: Разработка и актуализация бизнес-процессов | B9: Разработка, актуализация, унификация БП | C9: Унификация основных БП по ГК | D9: Пенский А.К. | E9: Разработан БП по премированию (совместно с Ереминой О. и Кузнецовой О.)
A10: Кадровое делопроизводство
A11: Текущая деятельность
A12: Приказы о премировании | B12: Сбор данных, проверка и оформление приказов. Передача в бухгалтерию копий приказов. | C12: Соблюдение законодательства РФ | D12: Кузнецова О.Н. | E12: Выполнено 100%
A13: Отчетность по премированию | B13: Сбор данных ежемесячно, составление свода за квартал, анализ квартального премирования | C13: Обоснование расходов для отчета руководству (Жихарев П., Торопов Р., Шигаев В., Кисловская И.) | D13: Кузнецова О.НН. | E13: Сформированы и отработаны сводные таблицы январь, февраль, март (включая свод за квартал). Выполнено 100% с союлюдением сроков, установленных БП. Участие в описании БП по премированию.
A14: Обоснование премирования | B14: Оформление служебных записок | C14: Обоснование расходов работодателя | D14: Кузнецова О.Н. | E14: Оформлены служебные записки к приказам за январь, февраль; прдготовлены проекты СЗ к приказам за март. Приказы и СЗ подготовлены и переданы на проверку аудиторам.
A15: Приказы о материальной помощи | B15: Оформляется по заявлению работника, согласовывается с ГД. | C15: Соблюдение законодательства РФ | D15: Кузнецова О.Н. | E15: Оформлено 12 приказов (с предоставлением подтверждающих документов передано в бухгалтерию). Документы подготовлены для проверки аудиторам.
A16: Прием на работу | B16: Оформление документов при приеме на работу: ТД, приказ, Соглашение о неразглашении конфиденциальной информации, документы по персональным данным, заявления, справки и т.д., внесение данных в базу 1С, подписание с работником | C16: Соблюдение законодательства РФ | D16: Афонина Ю.В. Башкирова Т.А. (ув.) | E16: 95 приемов на работу
A17: Увольнение | B17: Оформление увольнения по инициативе работника, по инициативе работодателя. Оформляются приказ, соглашение об увольнении, табель учета, вносится запись в тр. книжку или справка СТД-Р, ознакомление работника с документами | C17: Соблюдение законодательства РФ | D17: Афонина Ю.В. Башкирова Т.А. (ув.) | E17: 35 увольнений
B18: Решение сложных вопросов по увольнению работников | D18: Еремина О.А. Козлова Ю.В. | E18: Решены вопросы по 3 сложным увольнениям (Кравцов, Яворский, Тимохин)
A19: Переводы (изменение должностей, подразделений) | B19: Переводы оформляются по соглашению сторон (возможно в связи с изменением шатного расписания, на основании результатлов аттестации персонала), готовится: приказ, доп. соглашение к ТД, вносятся данные в программу 1С, ознакомление работника | C19: Соблюдение законодательства РФ | D19: Афонина Ю.В. Башкирова Т.А. (ув.) | E19: 67 приказов на переводы на другую работу, 650 изменений зп, 700 изменений графиков работы и видов начислений
A20: Отпуска, все виды (ежегодные, без сохранений з/п, учебные, по БИР, по уходу за ребенком, донорские, пр.) | B20: На основании графика отпусков или по заявлению работника оформляется приказ на отпуск с приложением необходимых подтверждающих документов | C20: Соблюдение законодательства РФ | D20: Афонина Ю.В. Башкирова Т.А. (ув.) Руцкая В.В. | E20: 318 приказов по всем видам отпусков и отсутствий
A21: Оформление сверхурочной работы, РВ | B21: На основании СЗ от руководителя и согласия работников оформляется Приказ (с офомлением повышенной оплаты или предоставлением днем отдыха) | C21: Соблюдение законодательства РФ | D21: Афонина Ю.В. - командировки Башкирова Т.А. (ув.) - командировки Руцкая В.В. - командировки Павленко Н.С. - все остальные | E21: 188 приказов
A22: Командировки | B22: Оформление приказов о командировании , изменении сроков командирования и контроль оформления Служебных заданий на командировки | C22: Соблюдение законодательства РФ | D22: Афонина Ю.В. Башкирова Т.А. (ув.) Руцкая В.В. | E22: 164 приказа на командировки и изменения сроков командировки
A23: Заключение ДС на питание | B23: Заключение ДС с работниками на подключение к питанию или отключение, передача данных в бухгалтерию | C23: Соблюдение законодательства РФ, гарантии работникам | D23: Еремина О.А. Афонина Ю.В. | E23: Заключены ДС с работниками на питаниее Руднево и Машково в полном объеме
A24: Аудит кадровых документов | B24: Проверка раличия и восстановление отсутствующих приказов за 2025 и при необходимости за 2024 кадровых приказов | C24: Соблюдение законодательства РФ | D24: Козлова Ю.В. Афонина Ю.В. Башкирова Т.А. (ув.) Марцулевич В.А. | E24: Проведен аудит, составлен список отсутствующих приказов, план восстановления документов
A25: Согласование, утверждение Положений и должностных инструкций по новому ШР в полном объеме
A26: Согласование ДИ по новой форме по всем должностям согласно ШР, подписание, передача на утверждение ГД | B26: Наличие базы ДИ и ПП по организации в полном объеме | C26: Соблюдение законодательства РФ | D26: Еремина О.А. Козлова Ю.В. | E26: 50% утвержденных ДИ и ПП, 25% ДИ в разработке, 25% - на согласовании
A27: Формирование отчётности
A28: Отчет по статистике | B28: П4 НЗ, ежеквартальный , за 4-й квартал 2025 | C28: Соблюдение законодательства РФ | D28: Еремина О.А. | E28: Выполнено 100%
A29: Отчёты в СФР штатные работники (прием/увольнение) | B29: Отчёт в СФР (по форме ЕФС-1 разд. 1.1.) оформляется не позднее одного рабочего дня после даты издания приказов о приеме, увольнении работников. | C29: Соблюдение законодательства РФ | D29: Афонина Ю.В. Башкирова Т.А. (ув.) Козлова Ю.В. | E29: Выполнено 100%
A30: Отчёты в СФР штатные работники (переводы) | B30: Отчёт в СФР (по форме ЕФС-1 разд. 1.1.) оформляется не позднее 25 числа месяца, следующего за отчетным месяцем издания приказов о переводе работников. А так же иным мероприятиям предусмотренным законодательствам РФ. | C30: Соблюдение законодательства РФ | D30: Афонина Ю.В. Башкирова Т.А. (ув.) Козлова Ю.В. | E30: Выполнено 100%
A31: Отчёты в СФР штатные работники (иные мероприятия) | B31: Отчёт в СФР (по форме ЕФС-1 разд. 1.2.) оформляется не позднее трех рабочих дней после даты издания приказов о предоставлении отпусков по БиР, ОПУХ работникам. | C31: Соблюдение законодательства РФ | D31: Еремина О.А. Козлова Ю.В. | E31: Выполнено 100%
A32: Отчет по инвалидам | B32: ежеквартальный | C32: Соблюдение законодательства РФ | D32: Козлова Ю.В. | E32: Выполнено 100%
A33: Разработка (актуализация) ЛНА, развитие процессов, создание Базы знаний по кадрам
A34: Утверждение Положения о разъездном характере работы | C34: Соблюдение законодательства РФ, Унификация ЛНА группы компаний. Регулирование трудовых отношений | D34: Еремина О.А. | E34: Положение на согласовании у юристов
A35: Оптимизация приказов по содержанию | B35: Оптимизация приказов, содержащих данные по наряд-заказам, с целью исключения их переделки, а также для своевременности издания приказов | C35: Соблюдение законодательства РФ, оптимизация БП | D35: Еремина О.А. | E35: Приказы на командировки не содержат больше информацию по наряд-заказам - нет необходимости переделывать приказы
A36: Изменение процессов взаимодействия между подразделениями | B36: Оптимизация взаимодействия между кадрами и бухгалтерией, разработка документооборота между кадрами и другими подразделениями | C36: Оптимизация взаимодействия работников подразделений и ОУП | D36: Еремина О.А. | E36: Оптимизирован БП по передаче документов в бухгалтерию
A37: Подготовка методических материалов по кадрам | B37: Формирование Базы знаний по кадровым направлениям (Прием, перевод, увольнение , пр.) . Подготовка Памяток для работников, шаблонов СЗ, Заявлений, размещение в Базе - по основным мероприятиям | C37: Оптимизация взаимодействия работников подразделений и ОУП. Повышение уровня сервиса для персонала | D37: Еремина О.А. | E37: Подготовлены БП с блок-схемами по командировкам, премированию
A38: Оптимизация текста трудорого договора | B38: Форма ТД, утвержденная в 2025 году, содержит избыточные пункты, не соответствует по отдельным пунктам нормам ТК РФ, запрос от юристов на внесение главы, касающейся интеллектуальной собственности | C38: Соблюдение законодательства РФ | D38: Еремина О.А. Пенский А.К. | E38: Обновленный текст ТД согласован с юристами, находится на рассмотрении у В. Шигаева
A39: Работа с суммированным учетом РВ (в рамках нового Положения о СУРВ), Графики работы подразделений с СУРВ, Табели подразделений
A40: Организация работы подразделений по графикам смен. Анализ и актуализация графиков работы (смен) работников. Подготовка приказов Приведение в соответствие ТД работников | B40: Соблюдение графиков производства. Разработка графиком для Отдела режима | C40: Организация деятельности подразделений, соблюдение требований ТК РФ | D40: Павленко Н.С. | E40: Контроль по предоставленным СЗ на привлечение к СУ и РВ, выявлены недостоверные данные - отклонено проведение приказов (контроль использования ФОТа)
A41: Организация работы с табелями | B41: Контроль, сопровождение оформления табелей | C41: Организация деятельности подразделений, соблюдение требований ТК РФ | D41: Руцкая В.В. Павленко Н.С. | E41: Выполнено 100%
A42: Новая организационная структура, штатное расписание компании
A43: Соблюдение нового штатного расписания и ФОТ | B43: Контроль исполнения ФОТ/ШР. Предоставление данных для приема на работу, переводов руководителям и в отдел подбора | C43: Организация деятельности компании | D43: Еремина О.А. | E43: Выполнено 100%
A44: Внесение изменений в 1С по новому ШР | B44: Согласование, внесение изменений в 1С | C44: Организация деятельности компании | D44: Еремина О.А. | E44: Проведено изменение зп с 01.02.2026, оптимизированы перечни видов начислений и графиков работ, внедрены по всем работникам, проведена работа по анализу установленных надбавок и сроков их действия, исправлены по 1С и бумажным документам
A45: Составление и реализация ОС | B45: Согласование новой организационной структуры, ее реализация | C45: Организация деятельности компании | D45: Еремина О.А. Пенский А.К. | E45: Совместная работа с А. Пенским
A46: Подготовка базы к переходу на новую 1С: ЗУП | C46: Организация деятельности компании | D46: Еремина О.А., Козлова Ю.В. | E46: Проведен анализ учета лимитов и остатков отпусков, внесены необходимые корректировки, проверка соответствия штатного расписания и штатных сотрудников (порядка 20 работников числились на закрытых позициях)
A47: Инвентаризация "мертвых душ" | B47: Контроль использования ФОТ | C47: Организация деятельности компании | D47: Еремина О.А. Пенский А.К. | E47: Проведена инвентаризация, выявлены 100% МД (4 чел.), проведены увольнения (работа совместно с А. Пенским)
A48: Ведение воинского учёта и бронирования
A49: Разъяснение правил воинского учета | B49: При приеме на работу. Ведение журнала. | C49: Соблюдение законодательства РФ. | D49: Козлова Ю.В. Афонина Ю.В. Кавыза О.Г. | E49: Выполнено 100%
A50: Ведение карточек ф.10 | B50: При приеме, переводе, изменении данных, увольнении | C50: Соблюдение законожательства РФ. | D50: Козлова Ю.В. Афонина Ю.В. Кавыза О.Г. | E50: Выполнено 100%
A51: Сведения при приеме/увольнении/переводе/ изменении др. (Приложение № 2 к Положению о ВУ) | B51: Документ направлется в военный комиссариат по месту жительства работника, в т.ч. | C51: Соблюдение законодательства РФ. | D51: Козлова Ю.В. Афонина Ю.В. Кавыза О.Г. | E51: Выполнено 100%
A52: Подготовка документов по ВУ на 2026 год | B52: Документ направлется в военный комиссариат для согласования с военкомом | C52: Соблюдение законодательства РФ | D52: Козлова Ю.В. Афонина Ю.В. Кавыза О.Г. | E52: Передан на согласование приказ о назначении нового ответственного за ВУ, согласован
A53: Отчетность | B53: Продление справки (с предоставлением карточки организации ф.18; ф.6 и ф.19) в районной комиссии по бронированию. Передача справки в военный комиссариат | C53: Соблюдение законодательства РФ. | D53: Козлова Ю.В. Афонина Ю.В. Кавыза О.Г. | E53: Выполнено 100%
A54: Ведение документации по бронированию | B54: Подготовка приказов о бронировании сотрудников | C54: Соблюдение законодателсьвта РФ. | D54: Кавыза О.Г. | E54: Выполнено 100%
B55: Подготовка Выписок из приказа о бронировании сотрудников | C55: Соблюдение законодательства РФ. | D55: Кавыза О.Г. | E55: Выполнено 100%
B56: Подготовлены и направлены в ВК выписки их проекта приказа обронировании | C56: Соблюдение законодательства РФ | D56: Кавыза О.Г. | E56: Выполнено 100%
B57: Оформление приказа о прекращении бронирования | C57: Соблюдение законодательства РФ | D57: Кавыза О.Г. | E57: Выполнено 100%
B58: Оформление выписок из проекта приказа о прекращении бронировании | C58: Соблюдение законодательства РФ | D58: Кавыза О.Г. | E58: Выполнено 100%
B59: Оформление сопроводительных писем к выпискам из приказов | C59: Соблюдение законодательства РФ | D59: Кавыза О.Г. | E59: Выполнено 100%
A60: Подготовка листков сообщений | B60: Документ выдается на руки сотрудники с целью посещения военкомата в связи с ихменением места жительства, состава семьи, образования и т.д. | C60: Соблюдение законодательства РФ | D60: Козлова Ю.В. Афонина Ю.В. Кавыза О.Г. | E60: Выполнено 100%
A61: Подготовка направления для постановки на ВУ | B61: Документ выдается на руки сотрудники с целью посещения военкомата для постановки на ВУ | C61: Соблюдение законодательства РФ | D61: Козлова Ю.В. Афонина Ю.В. Кавыза О.Г. | E61: Выполнено 100%
A62: Ведение журналов | B62: Журналы по работе, связанной с воинским учетом и бронированием. | C62: Соблюдение законодательства РФ | D62: Козлова Ю.В. Афонина Ю.В. Кавыза О.Г. | E62: Выполнено 100%
A63: Автоматизация в 1С ведения данных по ВУ и бронированию | B63: Внесение данных по бронированию в 1С: приказов, справок пр. документов | C63: Организация деятельности подразделения | D63: Козлова Ю.В. Кавыза О.Г. | E63: Задача с переходом на 2 квартал, процент исполнения на конец 1 квартала с учетом начала работ в марте - 20%
A64: Рекрутинг
A65: Набор технологов в АИ СН | B65: набор персонала на критичное направление | C65: Укомплектование отдела | D65: Осипова В. Блинова А. Новикова Ю. | E65: Набор на критическое направление направления: сборка композитов, мех.обработка 7 выходов за квартал
A66: Усиление ОП Жуковский | B66: Набор персонала по направлениям конструкторы, технологи | C66: Масштабирование компании, развитие нового филиала | D66: Осипова В., Блинова А. | E66: +4 сотрудника за квартал Также был организован и проведен опрос сотрудников - собрать ОС, кто хотел бы переехать. На текущий момент перевезли 1 сотрудника, в проработке еще варианты подразделений, готовых к переезду
A67: Актуализация плана подбора на квартал | B67: Вычитка всех вакансий, актуализация плана с руководителями, корректировки в ХФ и на HH.ru | C67: Повышение качества подбора персонала | D67: Пенский А. Осипова В., Шибалкова Ю. Ковалева Е. Блинова А. Исматова В. | E67: Работа с поступающими по плану и вне плана заявками на подбор персонала, редактирование под общий шаблон для размещения на ресурсах для поиска, добавление в хантфлоу, актуализация информации в вакансиях при необходимости
A68: Организация и контроль работы по проверке соискателей | B68: Проверка кандидатов на различного вида задолженности и наличие ЮР лиц и ИП в системе Кронос | C68: Проверка | D68: Ковалева Е. Осипова В. | E68: Своевременная проверка кандидатов в системе Кронос. При выявлении спорных моментов в отчете проведение совместной работы с внутренней службой СБ и согласование с их стороны
A70: Предварительные мед.осмотры | B70: Заключение новых и акттуализация уже имеющихся договоров с мед.центрами | C70: Проверка перед трудоустройством | D70: Ковалева Е. Шибалкова Ю. | E70: Продление договоров с медцентрами в Воронеже, Казани и Москве. С марта ОТ подписали новый договор с "Центр Авиамед". Передача дел в отдел по ОТ и ПБ
B71: Направление на предварительные мед. осмотры | D71: Ковалева Е. Блинова А. Исматова В. Новикова Ю. | E71: Своевременное направление кандидатов на медосмотры в соответствии с должностями. Взаимодействие с менеджерами медцентров по необходимости. При возникновении спорных моментов - взаимодействие с отделом ОТ
A72: Сбор рекомендаций с прошлых мест работ кандидатов | B72: Для руководящих и точечных должностей по запросу собираем рекомендации по кандидату перед выставлением оффера | C72: Повышение качества подбора персонала | D72: Шибалкова Ю. Ковалева Е. Исматова В. Новикова Ю. | E72: Ковалева Е.С.: сбор рекомендаций по 2 кандидатам Шибалкова Ю.: сбор рекомендаций по 3 кандидатам Исматова В.: сбор рекомендаций по 1 кандидату Блинова А.: сбор рекомендаций по 1 кандидату Новикова Ю.:Сбор рекомендаций по 2 кандидатам
A73: Мониторинг рынка труда | B73: Сбор и отражение в табличной форме данных | C73: Оценка ситуации на рынке труда для корректировки кадровой политики | D73: Осипова В. Блинова А. Шибалкова Ю. Исматова В. Новикова Ю. | E73: Проведение аналитики также по запросам руководителей смежных подразделений - проведена аналитика по специалистам ОУК в г.Дербент
A74: Альтернативные ресурсы привлечения кандидатов | B74: Поиск альтернативных вариантов размещения вакансий | C74: Увеличение потока кандидатов | D74: Осипова В., Блинова А. | E74: На рассмотрении варианты с газетами, ССУЗ и тд.
A75: Отчетность еженедельная/квартальная | B75: Заполнение форм отчетности | C75: Выполнение плана подбора | D75: Пенский А. Осипова В., Шибалкова Ю. Ковалева Е. Блинова А. Исматова В. Новикова Ю. | E75: Заполнение еженедельного отчета по актуальным статусам вакансий, количеству вышедших сотрудников Шибалкова Ю.А.: Еженедельные отчеты по выходам сотрудников
A76: Реферальная программа | B76: Отслеживание окончания ИС сотрудников по рекомендации | C76: Увеличение воронки кандидатов, развитие HR бренда работодателя | D76: Осипова В., Шибалкова Ю. Ковалева Е. Блинова А. Новикова Ю. | E76: Отработка поступающих кандидатов по рекомендации по реферальной программе. Отслечивание ИС, проведение промежуточных и по итогам ИС встреч с заказчиком и сотрудником
A77: ЛНА | B77: Актуализация Положения о подборе персонала | C77: Систематизация процесса, инструктирование руководителей. | D77: Осипова В. | E77: Положение утверждено и введено в действие.
A78: ЛНА | B78: Разработка и внедрение Положения об аттестации персонала | C78: Систематизация процесса, инструктирование руководителей. | D78: Осипова В. | E78: Положение разработано и введено в действие с 22 января 2026
A79: ЛНА | B79: Внедрение Кодекса этики и служебного поведения работников | C79: Систематизация процесса, усиление корп.культуры | D79: Осипова В. | E79: Кодекс введене в действие с 01.01.2026 Согласован и утвержден Приказом состав комиссии по этике
A80: ЛНА | B80: Разработка и внедрение Положений об адаптации и наставничестве | C80: Систематизация процесса, инструктирование руководителей. | D80: Осипова В. | E80: Проект Положений на согласовании, собраны первые замечания - на отработке
A81: Адаптация
A82: Онбординг | B82: Проведение краткой экскурсии для новых сотрудников и выдача Welcome Kit, знакомство с руководителем | C82: Адаптация новичков, снижение времени на включение в работу, снижение текучести. | D82: Осипова В. Шибалкова Ю. Ковалева Е. Блинова А. Котов И. Исматова В. | E82: Проведение экскурсий новым сотрудникам в 1 рабочий день выдача Welcome Kit, знакомство с руководителем и рабочим местом
B83: Создание приветственной страницы для новых сотрудников, аналогично ЦТП | C83: Адаптация новичков, снижение времени на включение в работу, снижение текучести. | D83: Осипова В. Котов И.
A84: Аттестация | B84: Проведение аттестации действующих сотрудников для повышения категории/разряда и уровня заработной платы, в соответствии с ШР | C84: Повышение категорий и разрядов действующих сотрудников | D84: Осипова В. Шибалкова Ю. Ковалева Е. Блинова А. | E84: Осипова В.: проведено 4 аттестации в ОП Машково, КБ и ПП6 - в качестве председателя аттестационной комиссии, утверждение схемы работы комиссии Ковалева Е.С.: проведено 6 аттестаций в Машково, 3 аттестации в Руднево Шибалкова Ю.: проведено 11 аттестаций в КБ Москва Блинова А.: проведено 6 аттестаций ПП6
A85: Разработка адаптационного листа для вновь принятых сотрудников | B85: Утверждение формы единого чек-листа | C85: Снижение текучести персонала, дальнейшее развитие персонала | D85: Блинова А. | E85: Чек-лист точечно внедрен на ключевые позиции, будет регламентирован в будущем Положении
A86: Общение по результатам ИС | B86: Встречи с сотрудниками на ИС и во время ИС Подготовка чек-листа для прошедших ИС и шаблона СЗ для изменений по результатам ИС | C86: Мониторинг состояния новичков на ИС, снижение текучести персонала, обсуждение дальнейшего развития | D86: Шибалкова Ю. Ковалева Е. Блинова А. Исматова В. | E86: Ковалева Е.С.: проведено 2 встречи по чек-листу по результатам ИС Шибалкова Ю. : проведено 3 встречи по чек-листу по результатам ИС+ 1 встреча по увольнению в связи с непрохождением ИС Исматова В.А.: проведено 15 встреч по чек-листу по результатам ИС + промежуточные встречи Блинова А: проведено 14 встреч по итогам ИС
A87: Общение по результатам ИС/работы - переговоры по увольнению сотрудника | B87: Встреча с сотрудником на протяжении ИС, с проблемными зонами | C87: Повышение эффективности команды, "отсев" сотрудников, которые не устраивают работодателя | D87: Пенский А. Шибалкова Ю. | E87: Пенский А.: организация сложных увольнений 2 сотрудников ОП Ульяновск Шибалкова Ю.: Увольнение Лаптевой Е. (начальник ОТД)
A88: Материальная и не материальная мотивация
A89: Питание Машково | B89: Изучить варианты организации питания | C89: Нематериальная мотивация | D89: Пенский А., Шибалкова Ю. | E89: Пенский А.: поиск и переговоры с поставщиком, утверждение схемы Шибалкова Ю.: Процесс согласования и подписания договора питания в Машково/Руднево
A90: ДМС | B90: Подключение сотрудников со сроком работы от 6 месяцев | C90: Нематериальная мотивация | D90: Осипова В. Тихонова П. | E90: Тихонова П.: подготовка списком на подключение Осипова В.: проверка и отправка заявлений на вгнесение изменений в РГС Проработка программы для ОП Ульяновск, переговоры со страховой и сотрудниками - для наиболее подходящей программы и наполнению
A91: Best Benefits | B91: Подключение сервиса для сотрудников АИ СН | C91: Нематериальная мотивация | D91: Осипова В. Котов И. | E91: Регулярные рассылки, инструктирование сотрудников по сервису
A92: Реализация плана обучения персонала | B92: План обучения согласован - актуализация планов на квартал, организация курсов | C92: Повышение компетенций сотрудников по профильным направлениям | D92: Осипова В. Шибалкова Ю. | E92: Шибалкова: организовано 15 обучений
A93: Развитие HR-бренда
A94: Happy Job | B94: Органиация,проведение встреч с руководителями/сотрудниками подразделений по результатам опроса вовлеченности персонала Happy Job | C94: Повышение показателей вовлеченности и лояльности | D94: Осипова В.,
A95: Встречи с сотрудниками по запросу от руководителей/размещенному резюме/exit-интервью | B95: По запросу | C95: Сбор информации о причинах увольнений и проблемах компании для проработки и устранения проблем | D95: Шибалкова Ю. Ковалева Е. Блинова А. | E95: Проведение встреч с действующими сотрудниками, обновившими резюме Ковалева Е.С. :проведено 2 встречи Шибалкова Ю.А..:проведено 2 встречи Блинова А.: проведено 2 exit-интервью
A96: Поздравления с ДР сотрудников | B96: Актуализация списков именинников на будущий месяц, сбор фотографий для поздравлений. Сбор/отправка в филиалы подарков на ДР для сотрудников | C96: Поддержание корп. культуры | D96: Шибалкова Ю. Котов И. | E96: Шибалкова Ю.: Актуализация списков именинников на будущий месяц
B97: Составление, подписание приказов, списков, ведомостей, договоров дарения на подарки | D97: Котов И. Ковалева Е. Исматова В. | E97: Ковалева Е., Исматова В.: подписание приказов, списков, ведомостей, договоров дарения на подарки
A98: Работа с СУЗами, ВУЗами, ярмарки вакансий | B98: Актуализация информации по сотрудничеству, участие в ярмарках вакансий | C98: Привлечь молодых специалистов на открытые вакансии , повышение узнаваемости бренда АИ СН | D98: Пенский А. Осипова В., Исматова В. Котов И. Бушуев Д. | E98: Участие в ярмарках вакансий, обработка полученных анкет/резюме Участие в 2 ярмарках: 18 февраля и 25 марта собрано около 100 анкет Проведены переговоры с руководством Площадки практической подготовки колледжей на предмет привлечения молодых специалистов для замещения вакантных должностей на основном производстве
A99: Автоматизация процессов и аналитика
A100: Хантфлоу | B100: Ведение базы кандидатов, отслеживание воронки подбора. | C100: Повышение качества подбора, снижение сроков | D100: Шибалкова Ю. Ковалева Е. Блинова А. Тихонова П. Исматова В. Новикова Ю. | E100: Поддержание базы кандидатов в актуальном состоянии (актуальные вакансии, количество, этапы подбора)
A101: Аналитика резюме кандидатов. Работающих сотрудников, обновляющих резюме | B101: Отслеживание баз резюме, аналитика | C101: Удержание персонала | D101: Шибалкова Ю. Ковалева Е. Тихонова П., Блинова А. Исматова В. | E101: Ковалева Е.С. :Отслеживание баз резюме Исматова В.: отслеживание обновленных резюме сотрудников, использование посторонних источников для полной картины баз резюме
...

Sheet Список уволенных
A1: ФИО сотрудника | B1: Отдел | C1: Должность | D1: Дата начала работы | E1: Дата увольнения | F1: Срок работы, в годах | G1: Причина увольнения | H1: Значимость для компании
A2: Шувалов Алексей Витальевич | B2: Управление | C2: Главный инженер | D2: 15.11.2024 | E2: 31.03.2026 | F2: =(E2-D2)/365 | G2: Инициатива сотрудника - нашел работу с бОльшей зп, не готов работать зам.нового ГИ | H2: 4 | J2: Значимость сотрудника для организации определяется по шкале от 0 до 5, где 0 - минимальное значение, 5 - максимальное
A3: Игошкина Ольга Вячеславовна | B3: Отдел сертификации авиационной техники | C3: Начальник отдела | D3: 02.05.2024 | E3: 19.01.2026 | F3: =(E3-D3)/365 | G3: Инициатива работодателя - не лояльное отношение к компании и руководтсу, не устраивает качество работы | H3: 3
A4: Кочетков Илья Анатольевич | B4: Отдел режима (Офис) | C4: Оперативный дежурный | D4: 01.07.2018 | E4: 06.01.2026 | F4: =(E4-D4)/365 | G4: Смерть сотрудника | H4: 4
A5: Рено Эдуар Марк Александр Луи | B5: Дирекция программ | C5: Руководитель проекта по разработке систем развлечения | D5: 18.05.2023 | E5: 11.03.2026 | F5: =(E5-D5)/365 | G5: Увольнение с основного места работы - перевод на основное место в АИ Казань | H5: 0
A6: Вертипрахов Сергей Валерьевич | B6: Дирекция программ | C6: Ведущий менеджер проектов | D6: 01.05.2019 | E6: 20.03.2026 | F6: =(E6-D6)/365 | G6: Инициатива работодателя - "мертвая душа" | H6: 0
A7: Тимохин Артем Юрьевич | B7: Дирекция программ | C7: Руководитель проекта | D7: 29.01.2024 | E7: 11.03.2026 | F7: =(E7-D7)/365 | G7: Увольнение с совместительства | H7: 0
A8: Новикова Юлия Алексеевна | B8: Отдел подбора и развития персонала | C8: Менеджер по подбору персонала | D8: 11.11.2025 | E8: 02.02.2026 | F8: =(E8-D8)/365 | G8: техническое увольнение - перевод на совместительство с основного места работы | H8: 0
A9: Ковальчук Елена Борисовна | B9: Отдел управления персоналом | C9: Ведущий специалист по воинскому учету | D9: 20.02.2025 | E9: 04.03.2026 | F9: =(E9-D9)/365 | G9: Инициатива работника - семейные причины, переезд | H9: 4
A10: Башкирова Татьяна Алексеевна | B10: Отдел управления персоналом | C10: Ведущий менеджер по персоналу | D10: 12.12.2025 | E10: 27.03.2026 | F10: =(E10-D10)/365 | G10: Инициатива работодателя - не устраивает качество/подход к работе | H10: 3
A11: Лаптева Елена Викторовна | B11: Отдел технической документации | C11: Начальник отдела | D11: 15.01.2026 | E11: 31.03.2026 | F11: =(E11-D11)/365 | G11: Инициатива работодателя - непрохождение ИС, низкое качество выполнения задач, конфликты с подчиненными | H11: 4
A12: Жабин Максим Сергеевич | B12: Отдел главного технолога | C12: Инженер - технолог 3 категории | D12: 19.08.2025 | E12: 14.01.2026 | F12: =(E12-D12)/365 | G12: Инициатива работодателя - не устраивает качество работы, прогулы | H12: 2
A13: Козлов Александр Анатольевич | B13: Отдел АСУП | C13: Начальник отдела | D13: 12.01.2026 | E13: 24.02.2026 | F13: =(E13-D13)/365 | G13: Инициатива работодателя - не устраивает качество работы, прогулы | H13: 4
A14: Гасанова Оксана Петровна | B14: Производственное подразделение №7 | C14: Кладовщик | D14: 02.09.2022 | E14: 25.02.2026 | F14: =(E14-D14)/365 | G14: Инициатива работодателя - низкое качество работы, много ошибок | H14: 3
... A36: Пимкин Андрей Владиславович | B36: Отдел интерьера | C36: Ведущий инженер - конструктор | D36: 17.12.2025 | E36: 27.02.2026 | F36: =(E36-D36)/365 | G36: Инициатива сотрудника - нашел другую работу в районе Сокола, с зп 230 тысяч на руки фикс + премии (пытались удержать, но не удалось) | H36: 4
A37: Давыдов Владимир Михайлович | B37: Управление | C37: Директор по безопасности | D37: 45587 | E37: 46115 | F37: 1.4 | G37: Техническое увольнение - перевод на ГД по ЗГТ | H37: 0
A38: Жихарев Павел Александрович | B38: Руководство | C38: Генеральный директор | D38: 45589 | E38: 46119 | F38: 1.5 | G38: Инициатива работодателя | H38: 5
A39: Полозов Георгий Борисович | B39: Мебельный участок | C39: Мастер участка | D39: 42303 | E39: 46122 | F39: 10.5 | G39: Инициатива работодателя - низкое качество работы, нелояльное отношение к работе | H39: 3
A40: Жихарева Любовь Игоревна | B40: Отдел по оптимизации производственных процессов | C40: Начальник отдела | D40: 45796 | E40: 46125 | F40: 0.9 | G40: Инициатива работодателя | H40: 3
A41: Мирошкин Александр Сергеевич | B41: Обособленное подразделение Машково | C41: Заместитель начальника производства | D41: 45558 | E41: 46126 | F41: 1.6 | G41: Инициатива работодателя | H41: 4
A42: Метелкин Дмитрий Геннадиевич | B42: Участок декоративной отделки | C42: Мастер участка | D42: 45608 | E42: 46135 | F42: 1.4 | G42: Инициатива работодателя - низкое качество работы | H42: 3
A43: Балюк Владислав Владимирович | B43: Отдел АСУП | C43: Ведущий специалист по сопровождению информационных систем жизненного цикла изделия | D43: 46140 | E43: 46142 | F43: 0 | G43: Инициатива работодателя - по причине проблем с СБ | H43: 3
A44: Жданова Юлия Николаевна | B44: Отдел технического контроля | C44: Инженер 3 категории | D44: 45873 | E44: 46142 | F44: 0.7 | G44: Инициатива сотрудника - трудно добираться до работы, проблемы в коммуникациях в коллективе | H44: 2
A45: Шатрова Виктория Игоревна | B45: Швейный участок | C45: Мастер участка | D45: 46051 | E45: 46142 | F45: 0.2 | G45: Инициатива работодателя - не прошла ИС | H45: 3
A46: Пугаченко Евгений Александрович | B46: Группа инженеров-технологов | C46: Ведущий инженер-технолог | D46: 46034 | E46: 46146 | F46: 0.3 | G46: Инициатива работодателя - низкое качество работы, не соответствует заявленной квалификации, не выдерживает сроки задач | H46: 2
A47: Мукин Кирилл Александрович | B47: Департамент управления производством | C47: Директор по производству | D47: 46100 | E47: 46154 | F47: 0.1 | G47: Техническое увольнение - перевод на основное на ЗГД по производству | H47: 0
A48: Силантьева Вероника Васильевна | B48: Обособленное подразделение Казань | C48: Инженер - технолог 2 категории | D48: 45856 | E48: 46154 | F48: 0.8 | G48: Инициатива сотрудника - не устраивает содержание работы + семейные обстоятельства. В дальнейшем возможно рассмотрит вариант перехода в АИ Казань | H48: 3
... A71: Петрунин Алексей Викторович | B71: Участок декоративной отделки | C71: Маляр 4 разряда | D71: 45994 | E71: 46202 | F71: 0.6 | G71: Инициатива работодателя - по состоянию здоровья, не прошел периодический медосмотр | H71: 3
A72: Богачук Павел Николаевич | B72: Планово-диспетчерский отдел | C72: Заместитель начальника отдела | D72: 46113 | E72: 46204 | F72: =(E72-D72)/365 | G72: Инициатива сотрудника - нашел работу с бОльшей зп и должностью (РП с 250 net), пробовали удержать, но пока предложить нечего, разошлись позитивно, готов вернуться в случае появления подходящих позиций | H72: 3
A73: Пугачев Антон Александрович | B73: Механический участок | C73: Оператор-наладчик станков с ЧПУ | D73: 45481 | E73: 46210 | F73: =(E73-D73)/365 | G73: Инициатива сотрудника - не сложились отношения с руководством. нашел другую работу с более интересным содержанием (хотя пытались перевести в Руднево). Ушел в ММЗ Скорость | H73: 3
A74: Сакулин Денис Валерьевич | B74: Производственное подразделение №6 | C74: Электромонтажник 4 разряда | D74: 45852 | E74: 46211 | F74: =(E74-D74)/365 | G74: Инициатива работодателя - низкое качетво работы | H74: 1
A75: Коровин Никита Александрович | B75: Производственное подразделение №6 | C75: Слесарь - сборщик 4 разряда | D75: 46127 | E75: 46211 | F75: =(E75-D75)/365 | G75: Инициатива работодателя - низкое качетво работы | H75: 1
A76: Ермаков Роман Николаевич | B76: Производственное подразделение №6 | C76: Слесарь - сборщик 5 разряда | D76: 45866 | E76: 46211 | F76: =(E76-D76)/365 | G76: Инициатива работодателя - низкое качетво работы | H76: 1
A77: Гладченко Анатолий Анатольевич | B77: Производственное подразделение №6 | C77: Слесарь - сборщик 4 разряда | D77: 45967 | E77: 46211 | F77: =(E77-D77)/365 | G77: Инициатива работодателя - низкое качетво работы | H77: 1
A78: Михалев Никита Алексеевич | B78: Производственное подразделение №6 | C78: Слесарь - сборщик 4 разряда | D78: 45967 | E78: 46211 | F78: =(E78-D78)/365 | G78: Инициатива работодателя - низкое качетво работы | H78: 1
A79: Юрасов Михаил Александрович | B79: Производственное подразделение №6 | C79: Электромонтажник 4 разряда | D79: 45831 | E79: 46211 | F79: =(E79-D79)/365 | G79: Инициатива работодателя - низкое качетво работы | H79: 1
A80: Балабаев Михаил Сергеевич | B80: Отдел информационных технологий | C80: Начальник отдела | D80: 46049 | E80: 46213 | F80: =(E80-D80)/365 | G80: Инициатива сотрудника - объем задач, не сложились отношения с руководством (ЗГД по ИТ) | H80: 4
A81: Антясова Татьяна Васильевна | B81: Планово-диспетчерский отдел | C81: Ведущий специалист по учету | D81: 45474 | E81: 46213 | F81: =(E81-D81)/365 | G81: Инициатива сотрудника - семейные обстоятельства | H81: 3
A82: Блощинский Антон Юрьевич | B82: Механический участок | C82: Слесарь механосборочных работ 6 разряда | D82: 45769 | E82: 46213 | F82: =(E82-D82)/365 | G82: Иициатива сотрудника - не сложились отношения с руководством | H82: 3
A83: Жижин Денис Михайлович | B83: Механический участок | C83: Оператор-наладчик станков с ЧПУ | D83: 45966 | E83: 46216 | F83: =(E83-D83)/365 | G83: Инициатива сотрудника - не сошлись во мнениях с руководством (по мнению сотрудника, его лишили премии за чужую ошибку. другого наладчика из-за чего были проблемы со станком) | H83: 3
... A99: Агапов Кирилл Сергеевич | B99: Отдел информационной безопасности | C99: Начальник отдела | D99: 45666 | E99: 46234 | F99: =(E99-D99)/365 | G99: Инициатива работодателя - низкое качество работы | H99: 4
A100: Свиридов Евгений Игоревич | B100: Производственное подразделение №6 | C100: Заместитель начальника производства | D100: 46237 | E100: 46234 | F100: 0 | G100: Техническое увольнение | H100: 0
A101: Лайтер Алексей Александрович | B101: Обособленное подразделение Руднево | C101: Руководитель Обособленного подразделения Руднево | D101: 45691 | E101: 46234 | F101: =(E101-D101)/365 | G101: Инициатива работодателя - низкое качество работы | H101: 4
A102: Голубев Сергей Евгеньевич | B102: Обособленное подразделение Казань | C102: Слесарь - сборщик 4 разряда | D102: 45883 | E102: 46237 | F102: =(E102-D102)/365 | G102: Инициатива сотрудника - не устраивали условия труда (на его взгляд много клепательных работ, вредности при этом нет) | H102: 3
A103: Новикова Юлия Алексеевна | B103: Отдел подбора и развития персонала | C103: Менеджер по подбору персонала | D103: 46064 | E103: 46237 | F103: =(E103-D103)/365 | G103: Техническое увольнение, перезаключение трудового договора на новый срок | H103: 0
A104: Марцулевич Валерия Александровна | B104: Отдел управления персоналом | C104: Младший специалист | D104: 46041 | E104: 46251 | F104: =(E104-D104)/365 | G104: Инициатива сотрудника - интенсивный темп работы, объем задач, содержание | H104: 2
A105: Пудовкин Алексей Владимирович | B105: Механический участок | C105: Оператор-наладчик станков с ЧПУ | D105: 45910 | E105: 46252 | F105: =(E105-D105)/365 | G105: Инициатива сотрудника - не сошлись с руководством, уходит к знакомым | H105: 3
A106: Кузнецов Павел Вячеславович | B106: Отдел АСУП | C106: Программист 1С | D106: 46195 | E106: 46255 | F106: =(E106-D106)/365 | G106: Техническое увольнение, перезаключение трудового договора на новый срок | H106: 0
A107: Грисли Иляна Викторовна | B107: Отдел охраны труда и промышленной безопасности | C107: Специалист по охране труда | D107: 46161 | E107: 46255 | F107: =(E107-D107)/365 | G107: Инициатива сотрудника - объем и содержание задач | H107: 2
A108: Агапова Алла Сергеевна | B108: Производственное подразделение №6 | C108: Диспетчер | D108: 46055 | E108: 46258 | F108: =(E108-D108)/365 | G108: Инициатива сотрудника - ушла вслед за бывшим руководителем площадки, удерживать не стали | H108: 2
A109: Булатов Даниил Олегович | B109: Отдел главного технолога | C109: Инженер - технолог 2 категории | D109: 45881 | E109: 46258 | F109: =(E109-D109)/365 | G109: Инициатива сотрудника - не сложились отношения с руководством. Но отметили неадекватное поведение с его стороны (какие-то ментальные расстройства), удерживать не стали. | H109: 3
A110: Тищенко Александр Валентинович | B110: Производственное подразделение №6 | C110: Инженер по пожарной безопасности и ГО ЧС | D110: 45721 | E110: 46259 | F110: =(E110-D110)/365 | G110: Техническое увольнение - с совместительства (остается на основной ставке АИ Воронеж) | H110: 0
A111: Кикоть Максим Борисович | B111: Отдел сертификации авиационной техники | C111: Специалист по сертификации | D111: 45621 | E111: 46260 | F111: =(E111-D111)/365 | G111: Инициатива работодателя - низкое качество работы, был на части ставки. Нашли замену на полную ставку. | H111: 1
A112: Сафонов Никита Романович | B112: Участок сборки | C112: Слесарь-сборщик 4 разряда | D112: 45006 | E112: 46262 | F112: =(E112-D112)/365 | G112: Инициатива сотрудника - переезд в другой город, семейные обстоятельства | H112: 3
... A133: Костюкович Наталия Алексеевна | B133: Отдел разработки кресел авиационных | C133: Инженер - конструктор 2 категории | D133: 45397 | E133: 46295 | F133: =(E133-D133)/365 | G133: Инициатива сотрудника - нашла работу с удаленко и бОльшей зп | H133: 3

Sheet Текучесть расчетный файл 2026
A1: ТЕКУЧЕСТЬ ПЕРСОНАЛА (нормальный показатель на производстве 10-15 %) (нормальный показатель для высокотехнологичных компаний 18%) | F1: ТЕКУЧЕСТЬ ПО СРОКУ РАБОТЫ
A2: 1 кв 2026 | C2: 2 кв 2026
B3: По штатному расписанию | D3: По штатному расписанию | F3: Количество уволенных по сроку работы | S3: Численность сотрудников | T3: Текучесть по сроку работы
A4: Численность сотрудников на 1 января 2026 | B4: 648 | C4: Численность сотрудников на 1 января 2026 | D4: 648 | F4: Срок работы сотрудника на момент увольнения | G4: январь | H4: февраль | I4: март | J4: апрель | K4: май | L4: июнь | M4: июль | N4: август | O4: сентябрь | P4: октябрь | Q4: ноябрь | R4: декабрь
A5: Численность сотрудников на 31 марта 2026 | B5: 708 | C5: Численность сотрудников на 30 июня 2026 | D5: 744 | F5: 0-3 мес | H5: 4 | I5: 1 | J5: 1 | K5: 3 | L5: 4 | M5: 4 | N5: 1 | S5: 40 | T5: =SUM(G5:R5)/S5*100%
A6: Среднесписочная численность на 31 марта 2026 | B6: 640.9 | C6: Среднесписочная численность на 30 июня 2026 | D6: 694.3 | F6: 3-12 мес | G6: 5 | H6: 5 | I6: 8 | J6: 3 | K6: 5 | L6: 8 | M6: 15 | N6: 10 | O6: 7 | S6: 96 | T6: =SUM(G6:R6)/S6*100%
A7: Принято за квартал | B7: 95 | C7: Принято за квартал | D7: 71 | F7: 1-3 года | G7: 1 | H7: 1 | I7: 4 | J7: 4 | K7: 1 | L7: 4 | M7: 9 | N7: 4 | O7: 6 | S7: 100 | T7: =SUM(G7:R7)/S7*100%
A8: Принято в рамках перевода по ГК | B8: 3 | C8: Принято в рамках перевода по ГК | D8: 2 | F8: 3-7 лет | H8: 1 | I8: 4 | L8: 1 | N8: 1 | S8: 48 | T8: =SUM(G8:R8)/S8*100%
A9: Уволено за квартал | B9: 35 | C9: Уволено за квартал | D9: 35 | F9: 7 лет+ | G9: 1 | J9: 1 | M9: 1 | N9: 2 | O9: 2 | S9: 140 | T9: =SUM(G9:R9)/S9*100%
A10: Уволено в рамках перевода по ГК | B10: 5 | C10: Уволено в рамках перевода по ГК | D10: 2 | F10: Всего уволенных | G10: =SUM(G5:R9)
A11: Показатель текучести | B11: =B9/B6 | C11: Показатель текучести | D11: =D9/D6
A12: 3 кв 2026 | C12: 4 кв 2026
B13: По штатному расписанию | D13: По штатному расписанию | F13: ТЕКУЧЕСТЬ ПО ДЕПАРТАМЕНТАМ
A14: Численность сотрудников на 1 января 2026 | B14: 648 | C14: Численность сотрудников на 1 января 2026 | D14: 648 | F14: Количество уволенных по департаментам
A15: Численность сотрудников на 30 сентября 2026 | B15: 737 | C15: Численность сотрудников на 31 декабря 2026 | D15: 0 | F15: Подразделение, из которого уволили сотрудников | G15: январь | H15: февраль | I15: март | J15: апрель | K15: май | L15: июнь | M15: июль | N15: август | O15: сентябрь | P15: октябрь | Q15: ноябрь | R15: декабрь | S15: Среднесписочная численность | T15: Текучесть по подразде лениям
A16: Среднесписочная численность на 30 сентября 2026 | B16: 691.9 | C16: Среднесписочная численность на 31 декабря 2026 | D16: 0 | F16: Руководство | J16: 1 | S16: 1 | T16: 1
A17: Принято за квартал | B17: 55 | C17: Принято за квартал | D17: 0 | F17: Управление | I17: 1 | J17: 1 | K17: 1 | S17: 11.5 | T17: 0.2609
A18: Принято в рамках перевода по ГК | B18: 4 | C18: Принято в рамках перевода по ГК | D18: 0 | F18: ОГК | I18: 1 | S18: 17.5 | T18: 0.0571
A19: Уволено за квартал | B19: 62 | C19: Уволено за квартал | D19: 0 | F19: КБ | H19: 1 | K19: 1 | L19: 1 | N19: 2 | O19: 1 | S19: 91.6 | T19: 0.0334
A20: Уволено в рамках перевода по ГК | B20: 0 | C20: Уволено в рамках перевода по ГК | D20: 0 | F20: ОГТ | G20: 1 | K20: 1 | L20: 1 | M20: 1 | N20: 1 | O20: 2 | S20: 42 | T20: 0.0787
A21: Показатель текучести | B21: =(B19/B16) | C21: Показатель текучести | D21: =(D19/D16) | F21: ОМТС | H21: 1 | I21: 2 | O21: 2 | S21: 18 | T21: 0.1667
F22: Склад | L22: 1 | M22: 1 | S22: 23.1 | T22: 0.0433
A23: СТРУКТУРА УВОЛЬНЕНИЙ ПО ПРИЧИНАМ 2026 | F23: Транспортный отдел
A24: Причина увольнения | B24: Количество уволенных по причине | C24: % | F24: СМК | G24: 1 | J24: 1 | N24: 1 | S24: 21.3 | T24: 0.0939
A25: Инициатива работодателя: | F25: ОУП | I25: 2 | L25: 1 | N25: 2 | S25: 68 | T25: 0.0441
A26: Не прошел ИС (низкое качество работы) | B26: 4 | C26: =B26/$B$53 | F26: ОПиРП | H26: 1 | K26: 1 | N26: 1 | S26: 6.6 | T26: 0.303
A27: Низкое качество работы, не выполнение функционала. | B27: 34 | C27: =B27/$B$53 | F27: Охрана труда | K27: 1 | N27: 1 | S27: 2.1 | T27: 0.4762
A28: Вредные привычки, прогулы и нарушение трудовой дисциплины | B28: 4 | C28: =B28/$B$53 | F28: Бухгалтерия
A29: Перевод в рамках ГК АИ | B29: 9 | C29: =B29/$B$53 | F29: Отдел дизайна | O29: 1 | S29: 9.2 | T29: 0.4762
A30: Истечение срока ТД | B30: 4 | C30: =B30/$B$53 | F30: ФЭО | N30: 1 | S30: 18.5 | T30: 0.4762
A31: Другие причины (проблемы с СБ и т.д.) | B31: 3 | C31: =B31/$B$53 | F31: ПЦ Машково | G31: 1 | H31: 2 | I31: 3 | J31: 4 | L31: 1 | M31: 6 | N31: 2 | S31: 213.1 | T31: 0.0516
A32: Инициатива сотрудника: | F32: ПЦ Руднево | J32: 1 | M32: 1 | N32: 1 | O32: 3 | S32: 47.6 | T32: 0.021
A33: Во время ИС не захотел работать у нас по любой причине | B33: 6 | C33: =B33/$B$53 | F33: ОП Воронеж (ПП6) | H33: 2 | I33: 1 | K33: 1 | L33: 10 | M33: 11 | N33: 2 | O33: 1 | S33: 79 | T33: 0.1772
A34: Неудовлетворенность заработной платой: не соответствует объему работы, не устраивает уровень в целом | B34: 18 | C34: =B34/$B$53 | F34: ПП Казань | G34: 1 | I34: 2 | K34: 1 | M34: 1 | N34: 1 | S34: 18.6 | T34: 0.2151
A35: Не устраивает система премирования | B35: 0 | C35: =B35/$B$53 | F35: ПП Ульяноск | K35: 1 | S35: 18 | T35: 0.0556
A36: Неудовлетворенность соц.пакетом | B36: 1 | C36: =B36/$B$53 | F36: ОП Жуковский | H36: 1 | S36: 17 | T36: 0.0588
A37: Неудовлетворенность содержанием работы, уровнем решаемых задач | B37: 12 | C37: =B37/$B$53 | F37: ОИБ | M37: 1 | S37: 2.7 | T37: 0.0588
A38: Желание сменить специализацию | B38: 1 | C38: =B38/$B$53 | F38: СГИ | H38: 1 | I38: 2 | M38: 2 | S38: 21 | T38: 0.1429
A39: Отсутствие возможности повышения квалификации (нет перспектив проф.роста) | B39: 1 | C39: =B39/$B$53 | F39: АХО | G39: 2 | M39: 2 | O39: 1 | S39: 10 | T39: 0.2
A40: Отсутствие системы карьерного роста (нет продвижения по службе) | B40: 6 | C40: =B40/$B$53 | F40: Отдел режима | G40: 1 | S40: 5 | T40: 0.2
A41: Чрезмерная нагрузка, интенсивные условия труда | B41: 9 | C41: =B41/$B$53 | F41: ОАСУП | H41: 1 | J41: 1 | N41: 1 | O41: 2 | S41: 5.2 | T41: 0.3846
A42: Не сложились отношения с руководством | B42: 12 | C42: =B42/$B$53 | F42: ОИТ | L42: 1 | M42: 1 | O42: 1 | S42: 7.3 | T42: 0.137
A43: Неудовлетворенность общим трудовым климатом, конфликты в коллективе | B43: 3 | C43: =B43/$B$53 | F43: ПДО | H43: 1 | L43: 1 | M43: 2 | N43: 2 | O43: 1 | S43: 22.7 | T43: 0.0881
A44: Желание работать удаленно или в гибридном формате | B44: 1 | C44: =B44/$B$53 | F44: Дирекция программ | I44: 3 | S44: 1 | T44: 3
A45: Другие причины (все другие причины, при увольнении по собственному желанию) | B45: 10 | C45: =B45/$B$53 | F45: Делопроизводство | K45: 1 | S45: 1 | T45: 1
A46: Выход на пенсию | B46: 1 | C46: =B46/$B$53 | F46: Всего уволенных | G46: =SUM(G16:R45)
A47: Неудобный график | B47: 3 | C47: =B47/$B$53
A48: Переезд на другое место жительства | B48: 4 | C48: =B48/$B$53
A49: Трудно добираться до места работы | B49: 5 | C49: =B49/$B$53
A50: Невозможно совмещать работу и учебу | B50: 1 | C50: =B50/$B$53
A51: Состояние здоровья | B51: 7 | C51: =B51/$B$53
A52: Армия/мобилизация | B52: 1 | C52: =B52/$B$53
A53: Итого | B53: =SUM(B25:B52) | C53: =SUM(C25:C52)
