Workbook

Sheet Свод бюджета
A1: Свод бюджета: учебный класс по охране труда, новый корпус (2027)
A2: ООО «Авиационные Интерьеры-СН». Три варианта оснащения; варианты накопительные (оптимальный включает базовый)
A4: Раздел | B4: Базовый, ₽ | C4: Оптимальный, ₽ | D4: Расширенный, ₽
A5: 1. Мебель и обустройство | B5: =SUMIFS(Смета!$G$5:$G$72,Смета!$B$5:$B$72,$A5,Смета!$H$5:$H$72,"Б") -> 1134000 | C5: =SUMIFS(Смета!$G$5:$G$72,Смета!$B$5:$B$72,$A5,Смета!$H$5:$H$72,"Б")+SUMIFS(Смета!$G$5:$G$72,Смета!$B$5:$B$72,$A5,Смета!$H$5:$H$72,"О") -> 1169000 | D5: =SUMIFS(Смета!$G$5:$G$72,Смета!$B$5:$B$72,$A5,Смета!$H$5:$H$72,"Б")+SUMIFS(Смета!$G$5:$G$72,Смета!$B$5:$B$72,$A5,Смета!$H$5:$H$72,"О")+SUMIFS(Смета!$G$5:$G$72,Смета!$B$5:$B$72,$A5,Смета!$H$5:$H$72,"Р") -> 1169000
A6: 2. Технические средства обучения и IT | B6: =SUMIFS(Смета!$G$5:$G$72,Смета!$B$5:$B$72,$A6,Смета!$H$5:$H$72,"Б") -> 1105000 | C6: =SUMIFS(Смета!$G$5:$G$72,Смета!$B$5:$B$72,$A6,Смета!$H$5:$H$72,"Б")+SUMIFS(Смета!$G$5:$G$72,Смета!$B$5:$B$72,$A6,Смета!$H$5:$H$72,"О") -> 1470000 | D6: =SUMIFS(Смета!$G$5:$G$72,Смета!$B$5:$B$72,$A6,Смета!$H$5:$H$72,"Б")+SUMIFS(Смета!$G$5:$G$72,Смета!$B$5:$B$72,$A6,Смета!$H$5:$H$72,"О")+SUMIFS(Смета!$G$5:$G$72,Смета!$B$5:$B$72,$A6,Смета!$H$5:$H$72,"Р") -> 2470000
A7: 3. ПО, электронные курсы, VR | B7: =SUMIFS(Смета!$G$5:$G$72,Смета!$B$5:$B$72,$A7,Смета!$H$5:$H$72,"Б") -> 530000 | C7: =SUMIFS(Смета!$G$5:$G$72,Смета!$B$5:$B$72,$A7,Смета!$H$5:$H$72,"Б")+SUMIFS(Смета!$G$5:$G$72,Смета!$B$5:$B$72,$A7,Смета!$H$5:$H$72,"О") -> 530000 | D7: =SUMIFS(Смета!$G$5:$G$72,Смета!$B$5:$B$72,$A7,Смета!$H$5:$H$72,"Б")+SUMIFS(Смета!$G$5:$G$72,Смета!$B$5:$B$72,$A7,Смета!$H$5:$H$72,"О")+SUMIFS(Смета!$G$5:$G$72,Смета!$B$5:$B$72,$A7,Смета!$H$5:$H$72,"Р") -> 3080000
A8: 4. Первая помощь (практика) | B8: =SUMIFS(Смета!$G$5:$G$72,Смета!$B$5:$B$72,$A8,Смета!$H$5:$H$72,"Б") -> 731500 | C8: =SUMIFS(Смета!$G$5:$G$72,Смета!$B$5:$B$72,$A8,Смета!$H$5:$H$72,"Б")+SUMIFS(Смета!$G$5:$G$72,Смета!$B$5:$B$72,$A8,Смета!$H$5:$H$72,"О") -> 831500 | D8: =SUMIFS(Смета!$G$5:$G$72,Смета!$B$5:$B$72,$A8,Смета!$H$5:$H$72,"Б")+SUMIFS(Смета!$G$5:$G$72,Смета!$B$5:$B$72,$A8,Смета!$H$5:$H$72,"О")+SUMIFS(Смета!$G$5:$G$72,Смета!$B$5:$B$72,$A8,Смета!$H$5:$H$72,"Р") -> 831500
A9: 5. СИЗ (демонстрационный комплект) | B9: =SUMIFS(Смета!$G$5:$G$72,Смета!$B$5:$B$72,$A9,Смета!$H$5:$H$72,"Б") -> 420000 | C9: =SUMIFS(Смета!$G$5:$G$72,Смета!$B$5:$B$72,$A9,Смета!$H$5:$H$72,"Б")+SUMIFS(Смета!$G$5:$G$72,Смета!$B$5:$B$72,$A9,Смета!$H$5:$H$72,"О") -> 540000 | D9: =SUMIFS(Смета!$G$5:$G$72,Смета!$B$5:$B$72,$A9,Смета!$H$5:$H$72,"Б")+SUMIFS(Смета!$G$5:$G$72,Смета!$B$5:$B$72,$A9,Смета!$H$5:$H$72,"О")+SUMIFS(Смета!$G$5:$G$72,Смета!$B$5:$B$72,$A9,Смета!$H$5:$H$72,"Р") -> 540000
A10: 6. Специфика производства и наглядность | B10: =SUMIFS(Смета!$G$5:$G$72,Смета!$B$5:$B$72,$A10,Смета!$H$5:$H$72,"Б") -> 673000 | C10: =SUMIFS(Смета!$G$5:$G$72,Смета!$B$5:$B$72,$A10,Смета!$H$5:$H$72,"Б")+SUMIFS(Смета!$G$5:$G$72,Смета!$B$5:$B$72,$A10,Смета!$H$5:$H$72,"О") -> 938000 | D10: =SUMIFS(Смета!$G$5:$G$72,Смета!$B$5:$B$72,$A10,Смета!$H$5:$H$72,"Б")+SUMIFS(Смета!$G$5:$G$72,Смета!$B$5:$B$72,$A10,Смета!$H$5:$H$72,"О")+SUMIFS(Смета!$G$5:$G$72,Смета!$B$5:$B$72,$A10,Смета!$H$5:$H$72,"Р") -> 1188000
A11: 7. Подготовка преподавателей | B11: =SUMIFS(Смета!$G$5:$G$72,Смета!$B$5:$B$72,$A11,Смета!$H$5:$H$72,"Б") -> 335000 | C11: =SUMIFS(Смета!$G$5:$G$72,Смета!$B$5:$B$72,$A11,Смета!$H$5:$H$72,"Б")+SUMIFS(Смета!$G$5:$G$72,Смета!$B$5:$B$72,$A11,Смета!$H$5:$H$72,"О") -> 335000 | D11: =SUMIFS(Смета!$G$5:$G$72,Смета!$B$5:$B$72,$A11,Смета!$H$5:$H$72,"Б")+SUMIFS(Смета!$G$5:$G$72,Смета!$B$5:$B$72,$A11,Смета!$H$5:$H$72,"О")+SUMIFS(Смета!$G$5:$G$72,Смета!$B$5:$B$72,$A11,Смета!$H$5:$H$72,"Р") -> 335000
A12: Итого по ценам 2026 г. | B12: =SUM(B5:B11) -> 4928500 | C12: =SUM(C5:C11) -> 5813500 | D12: =SUM(D5:D11) -> 9613500
A13: Индексация на 2027 г. | B13: =B12*'Исходные данные'!$B$28 -> 394280 | C13: =C12*'Исходные данные'!$B$28 -> 465080 | D13: =D12*'Исходные данные'!$B$28 -> 769080
A14: Итого по ценам 2027 г. | B14: =B12+B13 -> 5322780 | C14: =C12+C13 -> 6278580 | D14: =D12+D13 -> 10382580
A15: Резерв на непредвиденные расходы | B15: =B14*'Исходные данные'!$B$29 -> 532278 | C15: =C14*'Исходные данные'!$B$29 -> 627858 | D15: =D14*'Исходные данные'!$B$29 -> 1038258
A16: ВСЕГО ЗАЛОЖИТЬ В БЮДЖЕТ 2027 г. | B16: =B14+B15 -> 5855058 | C16: =C14+C15 -> 6906438 | D16: =D14+D15 -> 11420838
A18: Площадь помещения (рекомендуемая), м² | B18: =Площадь!E13 -> 174
A19: Ежегодные эксплуатационные расходы, ₽/год | B19: =Эксплуатация!C11 -> 540000
A21: Рекомендуемый вариант: Оптимальный.
A22: Базовый: минимум для самостоятельного обучения по ПП 2464, включая работы на высоте и электробезопасность.
A23: Оптимальный: + макет ЧПУ, газоанализатор, СИЗОД для окрасочных камер, звук, видеофиксация.
A24: Расширенный: + VR-комплекс, интерактивная панель, лазерный тренажёр пожаротушения, сенсорный киоск.
A25: Отделка помещения и инженерные сети (вентиляция, кондиционирование, освещение) в смету не входят: закладываются в проект корпуса.

Sheet Исходные данные
A1: Исходные данные и допущения
A2: Синий шрифт на жёлтом фоне: вводимые значения, можно менять. Остальные листы пересчитываются автоматически.
A4: Параметр | B4: Значение | C4: Ед. | D4: Источник / комментарий
A5: Численность работников в новом корпусе | B5: 500 | C5: чел. | D5: Данные предприятия
A6: Текучесть (принимаемые за год) | B6: 0.15 | C6: доля | D6: Допущение, уточнить у отдела кадров
A7: Доля работников, обучаемых по программе Б (вредные/опасные факторы) | B7: 0.7 | C7: доля | D7: Допущение по результатам СОУТ/ОПР, уточнить
A8: Доля работников, обучаемых по программе В (работы повышенной опасности) | B8: 0.3 | C8: доля | D8: Допущение, уточнить по перечню работ повышенной опасности
A9: Доля работников, обучаемых первой помощи | B9: 0.8 | C9: доля | D9: Допущение, перечень утверждает работодатель
A10: Доля работников, обучаемых применению СИЗ | B10: 0.7 | C10: доля | D10: Допущение, перечень СИЗ, требующих практических навыков
A11: Доля работников, выполняющих работы на высоте | B11: 0.1 | C11: доля | D11: Допущение, уточнить по перечню работ на высоте
A12: Численность электротехнического персонала | B12: 25 | C12: чел. | D12: Допущение, уточнить у главного энергетика
A13: Периодичность обучения | B13: 3 | C13: лет | D13: ПП РФ от 24.12.2021 № 2464: не реже 1 раза в 3 года
A14: Подрядчики/командированные на вводный инструктаж в год | B14: 100 | C14: чел. | D14: Допущение
A15: Часы: программа А | B15: 16 | C15: ч | D15: ПП 2464: не менее 16 ч
A16: Часы: программа Б | B16: 16 | C16: ч | D16: ПП 2464: не менее 16 ч
... A29: Резерв на непредвиденные расходы | B29: 0.1 | C29: доля | D29: Рекомендуемый бюджетный резерв

Sheet Потребность в обучении
A1: Расчёт потребности в обучении (п. 25 Приказа Минтруда № 894)
A2: Площадь класса определяется исходя из годовой потребности в обучении
A4: Программа | B4: Чел. в год | C4: Часов на 1 чел. | D4: Доля очно в классе | E4: Чел.-часов в классе
A5: Обучение по ОТ, программа А | B5: =ROUND('Исходные данные'!$B$5/'Исходные данные'!$B$13+'Исходные данные'!$B$5*'Исходные данные'!$B$6,0) -> 242 | C5: ='Исходные данные'!$B$15 -> 16 | D5: ='Исходные данные'!$B$23 -> 0.5 | E5: =B5*C5*D5 -> 1936
A6: Обучение по ОТ, программа Б | B6: =ROUND(('Исходные данные'!$B$5/'Исходные данные'!$B$13+'Исходные данные'!$B$5*'Исходные данные'!$B$6)*'Исходные данные'!$B$7,0) -> 169 | C6: ='Исходные данные'!$B$16 -> 16 | D6: ='Исходные данные'!$B$23 -> 0.5 | E6: =B6*C6*D6 -> 1352
A7: Обучение по ОТ, программа В | B7: =ROUND(('Исходные данные'!$B$5/'Исходные данные'!$B$13+'Исходные данные'!$B$5*'Исходные данные'!$B$6)*'Исходные данные'!$B$8,0) -> 73 | C7: ='Исходные данные'!$B$17 -> 16 | D7: ='Исходные данные'!$B$23 -> 0.5 | E7: =B7*C7*D7 -> 584
A8: Оказание первой помощи | B8: =ROUND(('Исходные данные'!$B$5/'Исходные данные'!$B$13+'Исходные данные'!$B$5*'Исходные данные'!$B$6)*'Исходные данные'!$B$9,0) -> 193 | C8: ='Исходные данные'!$B$18 -> 8 | D8: 1 | E8: =B8*C8*D8 -> 1544
A9: Применение СИЗ | B9: =ROUND(('Исходные данные'!$B$5/'Исходные данные'!$B$13+'Исходные данные'!$B$5*'Исходные данные'!$B$6)*'Исходные данные'!$B$10,0) -> 169 | C9: ='Исходные данные'!$B$19 -> 4 | D9: 1 | E9: =B9*C9*D9 -> 676
A10: Вводный инструктаж (новые работники + подрядчики) | B10: =ROUND('Исходные данные'!$B$5*'Исходные данные'!$B$6+'Исходные данные'!$B$14,0) -> 175 | C10: ='Исходные данные'!$B$20 -> 1.5 | D10: 1 | E10: =B10*C10*D10 -> 262.5
A11: Безопасные методы работ на высоте | B11: =ROUND(('Исходные данные'!$B$5/'Исходные данные'!$B$13+'Исходные данные'!$B$5*'Исходные данные'!$B$6)*'Исходные данные'!$B$11,0) -> 24 | C11: ='Исходные данные'!$B$21 -> 16 | D11: 1 | E11: =B11*C11*D11 -> 384
A12: Электробезопасность (ежегодно) | B12: ='Исходные данные'!$B$12 -> 25 | C12: ='Исходные данные'!$B$22 -> 8 | D12: 1 | E12: =B12*C12*D12 -> 200
A13: Итого чел.-часов в классе в год | E13: =SUM(E5:E12) -> 6938.5
A14: Доступный фонд времени класса, ч/год | E14: ='Исходные данные'!$B$24*'Исходные данные'!$B$25*'Исходные данные'!$B$26 -> 1296.75
A15: Средняя одновременная загрузка, чел. | E15: =E13/E14 -> 5.3506844
A16: Пиковая одновременная загрузка, чел. | E16: =E15*'Исходные данные'!$B$27 -> 13.376711
A17: Минимум мест обучения по п. 97 ПП 2464 (1 на 100 чел.) | E17: =ROUNDUP('Исходные данные'!$B$5/100,0) -> 5
A18: Принято мест в лекционной зоне (с учётом Дней ОТ, собраний, комиссий) | E18: 24

Sheet Площадь
A1: Расчёт площади учебного класса по зонам
A2: Норматив площади в Приказе 894 не установлен (п. 25); ниже расчёт от потребности и эргономических норм
A4: Зона | B4: Кол-во мест/позиций | C4: м² на место | D4: Доп. площадь, м² | E4: Итого, м² | F4: Обоснование
A5: Лекционная зона (теория, инструктажи, проверка знаний группой) | B5: ='Потребность в обучении'!$E$18 -> 24 | C5: 2.5 | D5: 10 | E5: =B5*C5+D5 -> 70 | F5: 2,5 м² на место + 10 м² зона преподавателя и экрана (практика проектирования учебных аудиторий)
A6: Практическая зона: первая помощь | B6: 2 | C6: 9 | D6: 0 | E6: =B6*C6+D6 -> 18 | F6: Свободный периметр 3x3 м вокруг манекена (п. 36 ПП 2464)
A7: Практическая зона: СИЗ, LOTO, макет станка, газоанализатор | B7: 1 | C7: 0 | D7: 22 | E7: =B7*C7+D7 -> 22 | F7: Витрины, манекены СИЗ, зеркало, макет (п. 39, 41 ПП 2464)
A8: Практическая зона: работы на высоте | B8: 1 | C8: 0 | D8: 12 | E8: =B8*C8+D8 -> 12 | F8: Стенд с анкерной линией, точка крепления 12 кН; потолок не ниже 3,5 м (782н)
A9: Практическая зона: электробезопасность | B9: 1 | C9: 0 | D9: 6 | E9: =B9*C9+D9 -> 6 | F9: Стенд-макет, средства защиты в электроустановках
A10: Зона проверки знаний (АРМ) | B10: 6 | C10: 4.5 | D10: 3 | E10: =B10*C10+D10 -> 30 | F10: 4,5 м² на рабочее место с ПЭВМ (СанПиН 1.2.3685-21); п. 97 ПП 2464
A11: Подсобное помещение (хранение тренажёров, СИЗ, расходников) | B11: 1 | C11: 0 | D11: 10 | E11: =B11*C11+D11 -> 10 | F11: Хранение без загромождения проходов
A12: Тамбур / гардероб | B12: 1 | C12: 0 | D12: 6 | E12: =B12*C12+D12 -> 6 | F12: Места для верхней одежды
A13: ИТОГО рекомендуемая площадь, м² | E13: =SUM(E5:E12) -> 174
A14: Минимально допустимо (зона проверки знаний совмещена с лекционной), м² | E14: =E13-E10 -> 144
A15: Справочно: прежняя норма Минтруда (Пост. № 7 от 17.01.2001, утратило силу), м² | E15: =24+MAX(0,ROUNDUP(('Исходные данные'!$B$5-1000)/1000,0))*6 -> 24
A17: Кабинет службы ОТ (рабочие места специалистов) является отдельным помещением и в расчёт не входит.

Sheet Смета
A1: Смета оснащения учебного класса по охране труда
A2: Цены ориентировочные, рынок РФ, III кв. 2026, с НДС 22%. Вариант: Б = базовый, О = добавляется в оптимальном, Р = добавляется в расширенном
A4: № | B4: Раздел | C4: Наименование | D4: Ед. | E4: Кол-во | F4: Цена, ₽ | G4: Сумма, ₽ | H4: Вариант | I4: Обоснование / источник
A5: 1 | B5: 1. Мебель и обустройство | C5: Стол ученический мобильный складной (на колёсах, трансформация рассадки) | D5: шт | E5: 24 | F5: 14000 | G5: =E5*F5 -> 336000 | H5: Б | I5: 24 места для групповых занятий
A6: 2 | B6: 1. Мебель и обустройство | C6: Стул для обучающихся штабелируемый | D6: шт | E6: 30 | F6: 5500 | G6: =E6*F6 -> 165000 | H6: Б | I6: 24 места + 6 резерв
A7: 3 | B7: 1. Мебель и обустройство | C7: Стол и кресло преподавателя | D7: компл | E7: 1 | F7: 45000 | G7: =E7*F7 -> 45000 | H7: Б | I7: Рабочее место специалиста (trudohrana.ru)
A8: 4 | B8: 1. Мебель и обустройство | C8: Кафедра (трибуна) лектора | D8: шт | E8: 1 | F8: 35000 | G8: =E8*F8 -> 35000 | H8: О | I8: Совет из материала «Как создать кабинет и уголок ОТ»
A9: 5 | B9: 1. Мебель и обустройство | C9: Шкаф застеклённый для НПА и документации | D9: шт | E9: 4 | F9: 28000 | G9: =E9*F9 -> 112000 | H9: Б | I9: Хранение НПА в застеклённых шкафах (материал PDF)
A10: 6 | B10: 1. Мебель и обустройство | C10: Витрина для демонстрации СИЗ | D10: шт | E10: 3 | F10: 45000 | G10: =E10*F10 -> 135000 | H10: Б | I10: Натурные образцы (п. 24 Приказа 894)
A11: 7 | B11: 1. Мебель и обустройство | C11: Стеллаж металлический для подсобного помещения | D11: шт | E11: 4 | F11: 12000 | G11: =E11*F11 -> 48000 | H11: Б | I11: Хранение тренажёров и СИЗ без загромождения проходов
A12: 8 | B12: 1. Мебель и обустройство | C12: Шкаф для верхней одежды | D12: шт | E12: 2 | F12: 22000 | G12: =E12*F12 -> 44000 | H12: Б | I12: Места для личных вещей (trudohrana.ru)
A13: 9 | B13: 1. Мебель и обустройство | C13: Стол компьютерный и кресло (зона проверки знаний) | D13: компл | E13: 6 | F13: 25000 | G13: =E13*F13 -> 150000 | H13: Б | I13: Под 6 АРМ проверки знаний
A14: 10 | B14: 1. Мебель и обустройство | C14: Зеркало ростовое для примерки СИЗ | D14: шт | E14: 1 | F14: 15000 | G14: =E14*F14 -> 15000 | H14: Б | I14: Отработка надевания СИЗ (п. 39 ПП 2464)
A15: 11 | B15: 1. Мебель и обустройство | C15: Коврик для отработки СЛР | D15: шт | E15: 4 | F15: 3500 | G15: =E15*F15 -> 14000 | H15: Б | I15: Практика первой помощи на полу
A16: 12 | B16: 1. Мебель и обустройство | C16: Рулонные шторы блэкаут / жалюзи | D16: компл | E16: 1 | F16: 70000 | G16: =E16*F16 -> 70000 | H16: Б | I16: Затемнение для видео (материал PDF, trudohrana.ru)
... A72: 68 | B72: 7. Подготовка преподавателей | C72: Разработка учебных программ и материалов проверки знаний (А, Б, В, ПП, СИЗ, высота) | D72: компл | E72: 1 | F72: 150000 | G72: =E72*F72 -> 150000 | H72: Б | I72: П. 96 ПП 2464: программы утверждает работодатель
C73: ИТОГО по всем позициям | G73: =SUM(G5:G72) -> 9613500

Sheet Эксплуатация
A1: Ежегодные эксплуатационные расходы (со 2-го года)
A2: Ориентировочно, с НДС
A4: Статья | B4: Обоснование | C4: Сумма, ₽/год
A5: Продление лицензии СДО | B5: Выгрузка результатов в реестр обученных лиц | C5: 300000
A6: Обновление библиотеки курсов и видеофильмов | B6: Изменения НПА | C6: 60000
A7: Расходные материалы для практики ПП | B7: Маски-клапаны, салфетки, перчатки, бинты | C7: 60000
A8: Обновление стендов и плакатов | B8: Изменения НПА и локальных актов | C8: 40000
A9: Обновление демонстрационных СИЗ | B9: Износ, смена поставщиков | C9: 50000
A10: Поверка газоанализатора, ТО тренажёров | B10: Ежегодная поверка средства измерения | C10: 30000
A11: ИТОГО в год | C11: =SUM(C5:C10) -> 540000
